kitoboy_optimizator/__init__.py
kitoboy_optimizator/multy_optimizer.py
kitoboy_optimizator/backtester/__init__.py
kitoboy_optimizator/backtester/backtester.py
kitoboy_optimizator/data_structures/__init__.py
kitoboy_optimizator/data_structures/backtest_results.py
kitoboy_optimizator/data_structures/downloading_ohlcv_result.py
kitoboy_optimizator/data_structures/downloading_task.py
kitoboy_optimizator/data_structures/optimization_task.py
kitoboy_optimizator/downloader/__init__.py
kitoboy_optimizator/downloader/data_downloader.py
kitoboy_optimizator/enums/__init__.py
kitoboy_optimizator/enums/enums.py
kitoboy_optimizator/exchanges/__init__.py
kitoboy_optimizator/exchanges/binance_futures_api.py
kitoboy_optimizator/exchanges/binance_spot_api.py
kitoboy_optimizator/exchanges/bybit_futures_api.py
kitoboy_optimizator/exchanges/enums.py
kitoboy_optimizator/exchanges/exceptions.py
kitoboy_optimizator/exchanges/abstract/__init__.py
kitoboy_optimizator/exchanges/abstract/exchange_api_adapter.py
kitoboy_optimizator/exchanges/abstract/request_builder.py
kitoboy_optimizator/exchanges/abstract/request_executor.py
kitoboy_optimizator/exchanges/bitget/__init__.py
kitoboy_optimizator/exchanges/bitget/async_api_requests_executor.py
kitoboy_optimizator/exchanges/bitget/bitget_futures_api.py
kitoboy_optimizator/exchanges/bitget/exceptions.py
kitoboy_optimizator/exchanges/bitget/request_builder.py
kitoboy_optimizator/exchanges/bitget/utils.py
kitoboy_optimizator/exchanges/schemas/__init__.py
kitoboy_optimizator/exchanges/schemas/api_request_schema.py
kitoboy_optimizator/exchanges/schemas/symbol_params_schema.py
kitoboy_optimizator/exchanges/utils/__init__.py
kitoboy_optimizator/exchanges/utils/filter_row_within_time_range.py
kitoboy_optimizator/exchanges/utils/retry_decorator.py
kitoboy_optimizator/http_session_manager/__init__.py
kitoboy_optimizator/http_session_manager/http_session_manager.py
kitoboy_optimizator/math/__init__.py
kitoboy_optimizator/math/math.py
kitoboy_optimizator-0.1.83.dist-info/METADATA
kitoboy_optimizator-0.1.83.dist-info/WHEEL
kitoboy_optimizator-0.1.83.dist-info/top_level.txt
kitoboy_optimizator-0.1.83.dist-info/RECORD
